universal_document_mcp/__init__.py
universal_document_mcp/__version__.py
universal_document_mcp/server.py
universal_document_mcp-1.0.0.dist-info/licenses/LICENSE
universal_document_mcp-1.0.0.dist-info/METADATA
universal_document_mcp-1.0.0.dist-info/WHEEL
universal_document_mcp-1.0.0.dist-info/entry_points.txt
universal_document_mcp-1.0.0.dist-info/top_level.txt
universal_document_mcp-1.0.0.dist-info/RECORD
